dashpool_pylibs/__init__.py
dashpool_pylibs/dfFilter.py
dashpool_pylibs/dfPlotter.py
dashpool_pylibs/dfStitcher.py
dashpool_pylibs/dfTrafos.py
dashpool_pylibs/flask.py
dashpool_pylibs/paramHandler.py
dashpool_pylibs/assets/__init__.py
dashpool_pylibs/assets/async-datepicker.js
dashpool_pylibs/assets/async-datepicker.js.map
dashpool_pylibs/assets/async-dropdown.js
dashpool_pylibs/assets/async-dropdown.js.map
dashpool_pylibs/assets/async-graph.js
dashpool_pylibs/assets/async-graph.js.map
dashpool_pylibs/assets/async-highlight.js
dashpool_pylibs/assets/async-highlight.js.map
dashpool_pylibs/assets/async-markdown.js
dashpool_pylibs/assets/async-markdown.js.map
dashpool_pylibs/assets/async-plotlyjs.js
dashpool_pylibs/assets/async-slider.js
dashpool_pylibs/assets/async-slider.js.map
dashpool_pylibs/assets/async-upload.js
dashpool_pylibs/assets/async-upload.js.map
dashpool_pylibs/assets/bootstrap.css
dashpool_pylibs/assets/custom-script.js
dashpool_pylibs/assets/dash_core_components-shared.js
dashpool_pylibs/assets/dash_core_components-shared.js.map
dashpool_pylibs/assets/dash_core_components.min.js
dashpool_pylibs/assets/dash_core_components.min.js.map
dashpool_pylibs/assets/favicon.ico
dashpool_pylibs/assets/metadata.json
dashpool_pylibs/assets/package-info.json
dashpool_pylibs/assets/plotly.min.js
dashpool_pylibs/assets/typography.css
dashpool_pylibs/dash_core_components/Checklist.py
dashpool_pylibs/dash_core_components/ConfirmDialog.py
dashpool_pylibs/dash_core_components/ConfirmDialogProvider.py
dashpool_pylibs/dash_core_components/DatePickerRange.py
dashpool_pylibs/dash_core_components/DatePickerSingle.py
dashpool_pylibs/dash_core_components/Dropdown.py
dashpool_pylibs/dash_core_components/Graph.py
dashpool_pylibs/dash_core_components/Input.py
dashpool_pylibs/dash_core_components/Interval.py
dashpool_pylibs/dash_core_components/Link.py
dashpool_pylibs/dash_core_components/Loading.py
dashpool_pylibs/dash_core_components/Location.py
dashpool_pylibs-2.1.11.dist-info/METADATA
dashpool_pylibs-2.1.11.dist-info/WHEEL
dashpool_pylibs-2.1.11.dist-info/top_level.txt
dashpool_pylibs-2.1.11.dist-info/RECORD
