Metadata-Version: 2.1
Name: dashpool-pylibs
Version: 2.1.11
Summary: Dash Pool Python Utilities
Home-page: http://krueckl.de
Author: Viktor Krueckl
Author-email: viktor@krueckl.de
License: UNKNOWN
Platform: UNKNOWN
